yandex_cloud_client/__init__.py
yandex_cloud_client/__main__.py
yandex_cloud_client/access.py
yandex_cloud_client/base.py
yandex_cloud_client/client.py
yandex_cloud_client/cloud.py
yandex_cloud_client/constants.py
yandex_cloud_client/error.py
yandex_cloud_client/folder.py
yandex_cloud_client/operation.py
yandex_cloud_client/version.py
yandex_cloud_client/zone.py
yandex_cloud_client/certificate/__init__.py
yandex_cloud_client/compute/__init__.py
yandex_cloud_client/compute/disk.py
yandex_cloud_client/compute/image.py
yandex_cloud_client/compute/instance.py
yandex_cloud_client/compute/instance_group.py
yandex_cloud_client/compute/placement_group.py
yandex_cloud_client/compute/snapshot.py
yandex_cloud_client/iam/__init__.py
yandex_cloud_client/iam/keys.py
yandex_cloud_client/iam/role.py
yandex_cloud_client/iam/service_account.py
yandex_cloud_client/iam/user_account.py
yandex_cloud_client/utils/__init__.py
yandex_cloud_client/utils/decorators.py
yandex_cloud_client/utils/endpoints.py
yandex_cloud_client/utils/helpers.py
yandex_cloud_client/utils/request.py
yandex_cloud_client/utils/response.py
yandex_cloud_client/vpc/__init__.py
yandex_cloud_client/vpc/address.py
yandex_cloud_client/vpc/network.py
yandex_cloud_client/vpc/network_interface.py
yandex_cloud_client/vpc/route_table.py
yandex_cloud_client/vpc/subnet.py
yandex_cloud_client-1.0.5.dist-info/AUTHORS
yandex_cloud_client-1.0.5.dist-info/LICENSE
yandex_cloud_client-1.0.5.dist-info/METADATA
yandex_cloud_client-1.0.5.dist-info/WHEEL
yandex_cloud_client-1.0.5.dist-info/top_level.txt
yandex_cloud_client-1.0.5.dist-info/RECORD
