Metadata-Version: 2.1
Name: yandex-cloud-client
Version: 1.0.5
Summary: PUnofficial Yandex.Cloud REST API Client
Home-page: https://github.com/akimrx/python-yc-client
Author: Akim Faskhutdinov
Author-email: akimstrong@yandex.ru
License: GPLv3
Keywords: yandex cloud client,rest api,yandex cloud client
Platform: osx
Platform: linux
Classifier: Programming Language :: Python :: 3.7
Classifier: Programming Language :: Python :: 3.8
Classifier: Operating System :: OS Independent
Classifier: Intended Audience :: Developers
Classifier: Intended Audience :: System Administrators
Requires-Python: >=3.7
Requires-Dist: cryptography
Requires-Dist: decorator (>=4.4.0)
Requires-Dist: pyjwt (>=1.7.1)
Requires-Dist: pyyaml
Requires-Dist: requests
